snakemd/__init__.py
snakemd/document.py
snakemd/elements.py
snakemd/templates.py
snakemd-2.2.1.dist-info/LICENSE
snakemd-2.2.1.dist-info/METADATA
snakemd-2.2.1.dist-info/WHEEL
snakemd-2.2.1.dist-info/RECORD
