Metadata-Version: 2.1
Name: snakemd
Version: 2.2.1
Summary: A markdown generation library for Python.
Home-page: https://www.snakemd.io
License: MIT
Author: Jeremy Grifski
Author-email: jeremy.grifski@therenegadecoder.com
Requires-Python: >=3.9,<4.0
Classifier: Development Status :: 5 - Production/Stable
Classifier: License :: OSI Approved :: MIT License
Classifier: Operating System :: OS Independent
Classifier: Programming Language :: Python :: 3
Classifier: Programming Language :: Python :: 3.9
Classifier: Programming Language :: Python :: 3.10
Classifier: Programming Language :: Python :: 3.11
Classifier: Programming Language :: Python :: 3.10
Classifier: Programming Language :: Python :: 3.11
Classifier: Programming Language :: Python :: 3.12
Classifier: Programming Language :: Python :: 3.13
Classifier: Programming Language :: Python :: 3.9
Classifier: Topic :: Documentation :: Sphinx
Project-URL: Changelog, https://www.snakemd.io/en/latest/version-history/
Project-URL: Documentation, https://www.snakemd.io/en/latest/docs/
Project-URL: Repository, https://github.com/TheRenegadeCoder/SnakeMD
